tb_common/__init__.py
tb_common/chdir.py
tb_common/dns.py
tb_common/utils/__init__.py
tb_common/utils/api.py
tb_common/utils/encrypt.py
tb_common/utils/numeric.py
tb_common/utils/processor_util.py
tb_common/utils/string_util.py
tb_common/utils/vietnamese.py
tb_common-0.1.2.dist-info/DESCRIPTION.rst
tb_common-0.1.2.dist-info/METADATA
tb_common-0.1.2.dist-info/RECORD
tb_common-0.1.2.dist-info/WHEEL
tb_common-0.1.2.dist-info/entry_points.txt
tb_common-0.1.2.dist-info/metadata.json
tb_common-0.1.2.dist-info/top_level.txt
