Metadata-Version: 2.0
Name: tb-common
Version: 0.1.2
Summary: UNKNOWN
Home-page: UNKNOWN
Author: Thong Dong
Author-email: thongdong7@gmail.com
License: UNKNOWN
Platform: UNKNOWN
Requires-Dist: six (==1.10.0)
